mcpw/__init__.py
mcpw/jupyter_functions.py
mcpw/manager.py
mcpw/mcstas_wrapper.py
mcpw/pyrightconfig.json
mcpw/setup.py
mcpw/setup_tools.py
mcpw-1.0.0.dist-info/LICENSE
mcpw-1.0.0.dist-info/METADATA
mcpw-1.0.0.dist-info/WHEEL
mcpw-1.0.0.dist-info/entry_points.txt
mcpw-1.0.0.dist-info/top_level.txt
mcpw-1.0.0.dist-info/RECORD
