Metadata-Version: 2.1
Name: mcpw
Version: 1.0.0
Summary: A lightweight and versitile McStas Python Wrapper for console and jupyter notebook
Author-email: Tincotema <tincotema@genthree.io>
Maintainer-email: Tincotema <tincotema@genthree.io>
License: MIT
Project-URL: Homepage, https://github.com/tincotema/mcstas-python-wrapper
Project-URL: Issues, https://github.com/tincotema/mcstas-python-wrapper/issues
Keywords: mcstas,jupyter,wrapper
Classifier: Development Status :: 4 - Beta
Classifier: Programming Language :: Python :: 3
Classifier: License :: OSI Approved :: MIT License
Classifier: Environment :: Console
Classifier: Operating System :: Microsoft :: Windows :: Windows 10
Classifier: Operating System :: POSIX :: Linux
License-File: LICENSE
